tavor/__init__.py
tavor/async_client.py
tavor/client.py
tavor/exceptions.py
tavor/models.py
tavor/sse_utils.py
tavor-1.4.3.dist-info/METADATA
tavor-1.4.3.dist-info/WHEEL
tavor-1.4.3.dist-info/licenses/LICENSE
tavor-1.4.3.dist-info/RECORD
