Metadata-Version: 2.4
Name: tavor
Version: 1.4.3
Summary: DEPRECATED: Use 'devento' package instead. Python SDK for Tavor cloud sandboxes
Project-URL: Homepage, https://github.com/tavor-dev/sdk-py
Project-URL: Issues, https://github.com/tavor-dev/sdk-py/issues
Project-URL: Documentation, https://tavor.dev
Author-email: Tavor <pkg@tavor.dev>
License: MIT
License-File: LICENSE
Classifier: Development Status :: 7 - Inactive
Classifier: Intended Audience :: Developers
Classifier: License :: OSI Approved :: MIT License
Classifier: Operating System :: OS Independent
Classifier: Programming Language :: Python :: 3
Classifier: Programming Language :: Python :: 3.9
Classifier: Programming Language :: Python :: 3.10
Classifier: Programming Language :: Python :: 3.11
Classifier: Programming Language :: Python :: 3.12
Classifier: Topic :: Software Development :: Libraries :: Python Modules
Requires-Python: >=3.9
Requires-Dist: requests>=2.28.0
Requires-Dist: typing-extensions>=4.0.0; python_version < '3.10'
Provides-Extra: async
Requires-Dist: aiohttp>=3.8.0; extra == 'async'
Provides-Extra: dev
Requires-Dist: aiohttp>=3.8.0; extra == 'dev'
Requires-Dist: black>=23.0.0; extra == 'dev'
Requires-Dist: build>=1.2.2; extra == 'dev'
Requires-Dist: mypy>=1.0.0; extra == 'dev'
Requires-Dist: pytest-asyncio>=0.21.0; extra == 'dev'
Requires-Dist: pytest-cov>=4.0.0; extra == 'dev'
Requires-Dist: pytest>=7.0.0; extra == 'dev'
Requires-Dist: ruff>=0.1.0; extra == 'dev'
Requires-Dist: twine>=6.1.0; extra == 'dev'
Requires-Dist: types-requests>=2.28.0; extra == 'dev'
